bwpmodule/BED.py
bwpmodule/__init__.py
bwpmodule/ireader.py
epiprofile-2.1.data/scripts/epidaurus.py
epiprofile-2.1.dist-info/COPYING
epiprofile-2.1.dist-info/METADATA
epiprofile-2.1.dist-info/WHEEL
epiprofile-2.1.dist-info/dependency_links.txt
epiprofile-2.1.dist-info/top_level.txt
epiprofile-2.1.dist-info/RECORD
